[
    {
    "id": 0,
    "url": "/img1.jpg",
    "title": "A few words about this blog platform, Ghost, and how this site was made",
    "body": "This lovely web is full of everything which is created I don't know what in mind, considering that sometimes totally bonkers stuff might be highly relevant if it has the right kind of thinking behind it.",
    "published_at": "Apr 15, 2020",
    "duration": 4,
    "author": "Mika Matikainen",
    "author_bild": "https://source.unsplash.com/random/100x100"
    }
]